<?xml version="1.0" encoding="UTF-8" standalone="no"?>
<departments>
	<department>
		<name>Department1</name>
		<employees>
			<employee>employee1@gmail.com</employee>
		</employees>
		<managers>
			<manager>manager1@gmail.com</manager>
			<manager>manager2@gmail.com</manager>
		</managers>
	</department>
	<department>
		<name>Department2</name>
		<employees>
			<employee>employee1@gmail.com</employee>
		</employees>
		<managers>
			<manager>manager1@gmail.com</manager>
		</managers>
	</department>
</departments>
